Workbook

Sheet Dashboard de Vendas
A1: DASHBOARD EXECUTIVO DE DESEMPENHO DE VENDAS
A3: Visão Consolidada de Faturamento, Margem de Lucro, Performance por Equipe e Produtos
A5: INDICADORES-CHAVE DE DESEMPENHO (KPIs)
A6: FATURAMENTO TOTAL | D6: LUCRO TOTAL ACUMULADO | G6: MARGEM DE LUCRO MÉDIA | J6: TOTAL DE PEDIDOS / VENDAS
A7: =SUM('Base de Dados'!J2:J151) | D7: =SUM('Base de Dados'!L2:L151) | G7: =D7/A7 | J7: =COUNTA('Base de Dados'!A2:A151)
G26: RANKING DE VENDEDORES (TOP PERFORMANCE)
G27: Vendedor | J27: Faturamento Total (R$)
G28: Ana Silva | J28: =SUMIF('Base de Dados'!E:E, G28, 'Base de Dados'!J:J)
G29: Carlos Souza | J29: =SUMIF('Base de Dados'!E:E, G29, 'Base de Dados'!J:J)
G30: Mariana Oliveira | J30: =SUMIF('Base de Dados'!E:E, G30, 'Base de Dados'!J:J)
G31: Lucas Ferreira | J31: =SUMIF('Base de Dados'!E:E, G31, 'Base de Dados'!J:J)
G32: Beatriz Costa | J32: =SUMIF('Base de Dados'!E:E, G32, 'Base de Dados'!J:J)

Sheet Base de Dados
A1: ID Pedido | B1: Data | C1: Mês/Ano | D1: Região | E1: Vendedor | F1: Categoria | G1: Produto | H1: Qtd | I1: Preço Unit. (R$) | J1: Faturamento (R$) | K1: Custo Total (R$) | L1: Lucro (R$)
A2: PED-1001 | B2: 46186 | C2: 2026-06 | D2: Sudeste | E2: Ana Silva | F2: Acessórios | G2: Webcam Full HD | H2: 4 | I2: 380 | J2: =H2*I2 | K2: =H2*220 | L2: =J2-K2
A3: PED-1002 | B3: 46080 | C3: 2026-02 | D3: Sul | E3: Ana Silva | F3: Acessórios | G3: Teclado Mecânico | H3: 10 | I3: 350 | J3: =H3*I3 | K3: =H3*200 | L3: =J3-K3
A4: PED-1003 | B4: 46131 | C4: 2026-04 | D4: Sudeste | E4: Ana Silva | F4: Eletrônicos | G4: Smartphone 5G | H4: 4 | I4: 2800 | J4: =H4*I4 | K4: =H4*1900 | L4: =J4-K4
A5: PED-1004 | B5: 46152 | C5: 2026-05 | D5: Norte | E5: Ana Silva | F5: Acessórios | G5: Mouse Vertical | H5: 9 | I5: 220 | J5: =H5*I5 | K5: =H5*120 | L5: =J5-K5
A6: PED-1005 | B6: 46130 | C6: 2026-04 | D6: Sul | E6: Lucas Ferreira | F6: Acessórios | G6: Webcam Full HD | H6: 1 | I6: 380 | J6: =H6*I6 | K6: =H6*220 | L6: =J6-K6
A7: PED-1006 | B7: 46217 | C7: 2026-07 | D7: Sul | E7: Lucas Ferreira | F7: Móveis | G7: Mesa Escritório L | H7: 3 | I7: 950 | J7: =H7*I7 | K7: =H7*600 | L7: =J7-K7
A8: PED-1007 | B8: 46078 | C8: 2026-02 | D8: Nordeste | E8: Ana Silva | F8: Eletrônicos | G8: Headset Sem Fio | H8: 2 | I8: 450 | J8: =H8*I8 | K8: =H8*250 | L8: =J8-K8
A9: PED-1008 | B9: 46114 | C9: 2026-04 | D9: Nordeste | E9: Beatriz Costa | F9: Móveis | G9: Cadeira Ergonômica | H9: 8 | I9: 1200 | J9: =H9*I9 | K9: =H9*750 | L9: =J9-K9
A10: PED-1009 | B10: 46160 | C10: 2026-05 | D10: Sudeste | E10: Lucas Ferreira | F10: Eletrônicos | G10: Monitor 27' 144Hz | H10: 10 | I10: 1600 | J10: =H10*I10 | K10: =H10*1100 | L10: =J10-K10
A11: PED-1010 | B11: 46249 | C11: 2026-08 | D11: Nordeste | E11: Beatriz Costa | F11: Eletrônicos | G11: Notebook Gamer | H11: 1 | I11: 4500 | J11: =H11*I11 | K11: =H11*3200 | L11: =J11-K11
A12: PED-1011 | B12: 46192 | C12: 2026-06 | D12: Sul | E12: Mariana Oliveira | F12: Eletrônicos | G12: Smartphone 5G | H12: 2 | I12: 2800 | J12: =H12*I12 | K12: =H12*1900 | L12: =J12-K12
A13: PED-1012 | B13: 46120 | C13: 2026-04 | D13: Nordeste | E13: Lucas Ferreira | F13: Acessórios | G13: Webcam Full HD | H13: 3 | I13: 380 | J13: =H13*I13 | K13: =H13*220 | L13: =J13-K13
A14: PED-1013 | B14: 46117 | C14: 2026-04 | D14: Nordeste | E14: Carlos Souza | F14: Acessórios | G14: Webcam Full HD | H14: 2 | I14: 380 | J14: =H14*I14 | K14: =H14*220 | L14: =J14-K14
A15: PED-1014 | B15: 46178 | C15: 2026-06 | D15: Sul | E15: Beatriz Costa | F15: Acessórios | G15: Mouse Vertical | H15: 3 | I15: 220 | J15: =H15*I15 | K15: =H15*120 | L15: =J15-K15
A16: PED-1015 | B16: 46141 | C16: 2026-04 | D16: Centro-Oeste | E16: Mariana Oliveira | F16: Acessórios | G16: Mouse Vertical | H16: 6 | I16: 220 | J16: =H16*I16 | K16: =H16*120 | L16: =J16-K16
A17: PED-1016 | B17: 46238 | C17: 2026-08 | D17: Sudeste | E17: Carlos Souza | F17: Eletrônicos | G17: Monitor 27' 144Hz | H17: 7 | I17: 1600 | J17: =H17*I17 | K17: =H17*1100 | L17: =J17-K17
A18: PED-1017 | B18: 46091 | C18: 2026-03 | D18: Sudeste | E18: Carlos Souza | F18: Acessórios | G18: Webcam Full HD | H18: 4 | I18: 380 | J18: =H18*I18 | K18: =H18*220 | L18: =J18-K18
A19: PED-1018 | B19: 46190 | C19: 2026-06 | D19: Centro-Oeste | E19: Lucas Ferreira | F19: Acessórios | G19: Suporte Monitor | H19: 3 | I19: 150 | J19: =H19*I19 | K19: =H19*80 | L19: =J19-K19
A20: PED-1019 | B20: 46090 | C20: 2026-03 | D20: Sul | E20: Carlos Souza | F20: Acessórios | G20: Webcam Full HD | H20: 10 | I20: 380 | J20: =H20*I20 | K20: =H20*220 | L20: =J20-K20
A21: PED-1020 | B21: 46132 | C21: 2026-04 | D21: Norte | E21: Lucas Ferreira | F21: Móveis | G21: Cadeira Ergonômica | H21: 3 | I21: 1200 | J21: =H21*I21 | K21: =H21*750 | L21: =J21-K21
A22: PED-1021 | B22: 46153 | C22: 2026-05 | D22: Centro-Oeste | E22: Ana Silva | F22: Eletrônicos | G22: Notebook Gamer | H22: 3 | I22: 4500 | J22: =H22*I22 | K22: =H22*3200 | L22: =J22-K22
A23: PED-1022 | B23: 46183 | C23: 2026-06 | D23: Sul | E23: Lucas Ferreira | F23: Acessórios | G23: Teclado Mecânico | H23: 7 | I23: 350 | J23: =H23*I23 | K23: =H23*200 | L23: =J23-K23
A24: PED-1023 | B24: 46120 | C24: 2026-04 | D24: Norte | E24: Lucas Ferreira | F24: Acessórios | G24: Webcam Full HD | H24: 9 | I24: 380 | J24: =H24*I24 | K24: =H24*220 | L24: =J24-K24
A25: PED-1024 | B25: 46243 | C25: 2026-08 | D25: Sudeste | E25: Ana Silva | F25: Acessórios | G25: Webcam Full HD | H25: 6 | I25: 380 | J25: =H25*I25 | K25: =H25*220 | L25: =J25-K25
A26: PED-1025 | B26: 46051 | C26: 2026-01 | D26: Nordeste | E26: Lucas Ferreira | F26: Eletrônicos | G26: Headset Sem Fio | H26: 1 | I26: 450 | J26: =H26*I26 | K26: =H26*250 | L26: =J26-K26
A27: PED-1026 | B27: 46207 | C27: 2026-07 | D27: Nordeste | E27: Beatriz Costa | F27: Eletrônicos | G27: Notebook Gamer | H27: 5 | I27: 4500 | J27: =H27*I27 | K27: =H27*3200 | L27: =J27-K27
A28: PED-1027 | B28: 46238 | C28: 2026-08 | D28: Norte | E28: Beatriz Costa | F28: Eletrônicos | G28: Smartphone 5G | H28: 6 | I28: 2800 | J28: =H28*I28 | K28: =H28*1900 | L28: =J28-K28
A29: PED-1028 | B29: 46218 | C29: 2026-07 | D29: Sul | E29: Beatriz Costa | F29: Acessórios | G29: Teclado Mecânico | H29: 10 | I29: 350 | J29: =H29*I29 | K29: =H29*200 | L29: =J29-K29
A30: PED-1029 | B30: 46105 | C30: 2026-03 | D30: Centro-Oeste | E30: Ana Silva | F30: Eletrônicos | G30: Monitor 27' 144Hz | H30: 5 | I30: 1600 | J30: =H30*I30 | K30: =H30*1100 | L30: =J30-K30
A31: PED-1030 | B31: 46084 | C31: 2026-03 | D31: Sudeste | E31: Carlos Souza | F31: Acessórios | G31: Teclado Mecânico | H31: 2 | I31: 350 | J31: =H31*I31 | K31: =H31*200 | L31: =J31-K31
A32: PED-1031 | B32: 46210 | C32: 2026-07 | D32: Centro-Oeste | E32: Ana Silva | F32: Acessórios | G32: Mouse Vertical | H32: 3 | I32: 220 | J32: =H32*I32 | K32: =H32*120 | L32: =J32-K32
A33: PED-1032 | B33: 46191 | C33: 2026-06 | D33: Centro-Oeste | E33: Beatriz Costa | F33: Eletrônicos | G33: Monitor 27' 144Hz | H33: 9 | I33: 1600 | J33: =H33*I33 | K33: =H33*1100 | L33: =J33-K33
A34: PED-1033 | B34: 46246 | C34: 2026-08 | D34: Norte | E34: Lucas Ferreira | F34: Eletrônicos | G34: Smartphone 5G | H34: 5 | I34: 2800 | J34: =H34*I34 | K34: =H34*1900 | L34: =J34-K34
A35: PED-1034 | B35: 46125 | C35: 2026-04 | D35: Nordeste | E35: Lucas Ferreira | F35: Acessórios | G35: Suporte Monitor | H35: 2 | I35: 150 | J35: =H35*I35 | K35: =H35*80 | L35: =J35-K35
A36: PED-1035 | B36: 46086 | C36: 2026-03 | D36: Sul | E36: Ana Silva | F36: Móveis | G36: Cadeira Ergonômica | H36: 10 | I36: 1200 | J36: =H36*I36 | K36: =H36*750 | L36: =J36-K36
A37: PED-1036 | B37: 46164 | C37: 2026-05 | D37: Sul | E37: Beatriz Costa | F37: Eletrônicos | G37: Notebook Gamer | H37: 2 | I37: 4500 | J37: =H37*I37 | K37: =H37*3200 | L37: =J37-K37
A38: PED-1037 | B38: 46204 | C38: 2026-07 | D38: Sudeste | E38: Carlos Souza | F38: Eletrônicos | G38: Notebook Gamer | H38: 6 | I38: 4500 | J38: =H38*I38 | K38: =H38*3200 | L38: =J38-K38
A39: PED-1038 | B39: 46041 | C39: 2026-01 | D39: Norte | E39: Carlos Souza | F39: Móveis | G39: Estante de Livros | H39: 8 | I39: 500 | J39: =H39*I39 | K39: =H39*300 | L39: =J39-K39
A40: PED-1039 | B40: 46077 | C40: 2026-02 | D40: Norte | E40: Carlos Souza | F40: Acessórios | G40: Suporte Monitor | H40: 4 | I40: 150 | J40: =H40*I40 | K40: =H40*80 | L40: =J40-K40
A41: PED-1040 | B41: 46223 | C41: 2026-07 | D41: Centro-Oeste | E41: Lucas Ferreira | F41: Eletrônicos | G41: Notebook Gamer | H41: 2 | I41: 4500 | J41: =H41*I41 | K41: =H41*3200 | L41: =J41-K41
A42: PED-1041 | B42: 46191 | C42: 2026-06 | D42: Centro-Oeste | E42: Mariana Oliveira | F42: Móveis | G42: Mesa Escritório L | H42: 8 | I42: 950 | J42: =H42*I42 | K42: =H42*600 | L42: =J42-K42
A43: PED-1042 | B43: 46244 | C43: 2026-08 | D43: Sudeste | E43: Ana Silva | F43: Eletrônicos | G43: Headset Sem Fio | H43: 6 | I43: 450 | J43: =H43*I43 | K43: =H43*250 | L43: =J43-K43
A44: PED-1043 | B44: 46227 | C44: 2026-07 | D44: Sudeste | E44: Carlos Souza | F44: Eletrônicos | G44: Smartphone 5G | H44: 9 | I44: 2800 | J44: =H44*I44 | K44: =H44*1900 | L44: =J44-K44
A45: PED-1044 | B45: 46137 | C45: 2026-04 | D45: Sul | E45: Lucas Ferreira | F45: Eletrônicos | G45: Monitor 27' 144Hz | H45: 8 | I45: 1600 | J45: =H45*I45 | K45: =H45*1100 | L45: =J45-K45
A46: PED-1045 | B46: 46086 | C46: 2026-03 | D46: Sudeste | E46: Lucas Ferreira | F46: Acessórios | G46: Teclado Mecânico | H46: 1 | I46: 350 | J46: =H46*I46 | K46: =H46*200 | L46: =J46-K46
A47: PED-1046 | B47: 46189 | C47: 2026-06 | D47: Norte | E47: Ana Silva | F47: Eletrônicos | G47: Smartphone 5G | H47: 3 | I47: 2800 | J47: =H47*I47 | K47: =H47*1900 | L47: =J47-K47
A48: PED-1047 | B48: 46127 | C48: 2026-04 | D48: Centro-Oeste | E48: Lucas Ferreira | F48: Eletrônicos | G48: Headset Sem Fio | H48: 1 | I48: 450 | J48: =H48*I48 | K48: =H48*250 | L48: =J48-K48
A49: PED-1048 | B49: 46065 | C49: 2026-02 | D49: Centro-Oeste | E49: Ana Silva | F49: Móveis | G49: Mesa Escritório L | H49: 8 | I49: 950 | J49: =H49*I49 | K49: =H49*600 | L49: =J49-K49
A50: PED-1049 | B50: 46096 | C50: 2026-03 | D50: Centro-Oeste | E50: Beatriz Costa | F50: Acessórios | G50: Suporte Monitor | H50: 3 | I50: 150 | J50: =H50*I50 | K50: =H50*80 | L50: =J50-K50
A51: PED-1050 | B51: 46071 | C51: 2026-02 | D51: Nordeste | E51: Carlos Souza | F51: Eletrônicos | G51: Notebook Gamer | H51: 6 | I51: 4500 | J51: =H51*I51 | K51: =H51*3200 | L51: =J51-K51
A52: PED-1051 | B52: 46037 | C52: 2026-01 | D52: Sudeste | E52: Beatriz Costa | F52: Móveis | G52: Estante de Livros | H52: 9 | I52: 500 | J52: =H52*I52 | K52: =H52*300 | L52: =J52-K52
A53: PED-1052 | B53: 46063 | C53: 2026-02 | D53: Sudeste | E53: Beatriz Costa | F53: Eletrônicos | G53: Smartphone 5G | H53: 2 | I53: 2800 | J53: =H53*I53 | K53: =H53*1900 | L53: =J53-K53
A54: PED-1053 | B54: 46175 | C54: 2026-06 | D54: Sudeste | E54: Carlos Souza | F54: Móveis | G54: Cadeira Ergonômica | H54: 10 | I54: 1200 | J54: =H54*I54 | K54: =H54*750 | L54: =J54-K54
A55: PED-1054 | B55: 46086 | C55: 2026-03 | D55: Norte | E55: Beatriz Costa | F55: Eletrônicos | G55: Notebook Gamer | H55: 7 | I55: 4500 | J55: =H55*I55 | K55: =H55*3200 | L55: =J55-K55
A56: PED-1055 | B56: 46191 | C56: 2026-06 | D56: Norte | E56: Beatriz Costa | F56: Acessórios | G56: Webcam Full HD | H56: 5 | I56: 380 | J56: =H56*I56 | K56: =H56*220 | L56: =J56-K56
A57: PED-1056 | B57: 46075 | C57: 2026-02 | D57: Nordeste | E57: Carlos Souza | F57: Móveis | G57: Mesa Escritório L | H57: 3 | I57: 950 | J57: =H57*I57 | K57: =H57*600 | L57: =J57-K57
A58: PED-1057 | B58: 46194 | C58: 2026-06 | D58: Nordeste | E58: Lucas Ferreira | F58: Móveis | G58: Cadeira Ergonômica | H58: 1 | I58: 1200 | J58: =H58*I58 | K58: =H58*750 | L58: =J58-K58
A59: PED-1058 | B59: 46140 | C59: 2026-04 | D59: Norte | E59: Beatriz Costa | F59: Eletrônicos | G59: Notebook Gamer | H59: 9 | I59: 4500 | J59: =H59*I59 | K59: =H59*3200 | L59: =J59-K59
A60: PED-1059 | B60: 46077 | C60: 2026-02 | D60: Norte | E60: Mariana Oliveira | F60: Eletrônicos | G60: Monitor 27' 144Hz | H60: 2 | I60: 1600 | J60: =H60*I60 | K60: =H60*1100 | L60: =J60-K60
A61: PED-1060 | B61: 46248 | C61: 2026-08 | D61: Sul | E61: Mariana Oliveira | F61: Móveis | G61: Cadeira Ergonômica | H61: 8 | I61: 1200 | J61: =H61*I61 | K61: =H61*750 | L61: =J61-K61
A62: PED-1061 | B62: 46236 | C62: 2026-08 | D62: Norte | E62: Mariana Oliveira | F62: Acessórios | G62: Teclado Mecânico | H62: 9 | I62: 350 | J62: =H62*I62 | K62: =H62*200 | L62: =J62-K62
A63: PED-1062 | B63: 46099 | C63: 2026-03 | D63: Sudeste | E63: Carlos Souza | F63: Móveis | G63: Cadeira Ergonômica | H63: 2 | I63: 1200 | J63: =H63*I63 | K63: =H63*750 | L63: =J63-K63
A64: PED-1063 | B64: 46213 | C64: 2026-07 | D64: Norte | E64: Carlos Souza | F64: Móveis | G64: Mesa Escritório L | H64: 10 | I64: 950 | J64: =H64*I64 | K64: =H64*600 | L64: =J64-K64
A65: PED-1064 | B65: 46076 | C65: 2026-02 | D65: Nordeste | E65: Carlos Souza | F65: Acessórios | G65: Webcam Full HD | H65: 9 | I65: 380 | J65: =H65*I65 | K65: =H65*220 | L65: =J65-K65
A66: PED-1065 | B66: 46148 | C66: 2026-05 | D66: Nordeste | E66: Ana Silva | F66: Eletrônicos | G66: Headset Sem Fio | H66: 5 | I66: 450 | J66: =H66*I66 | K66: =H66*250 | L66: =J66-K66
A67: PED-1066 | B67: 46034 | C67: 2026-01 | D67: Sudeste | E67: Mariana Oliveira | F67: Eletrônicos | G67: Monitor 27' 144Hz | H67: 3 | I67: 1600 | J67: =H67*I67 | K67: =H67*1100 | L67: =J67-K67
A68: PED-1067 | B68: 46212 | C68: 2026-07 | D68: Centro-Oeste | E68: Beatriz Costa | F68: Acessórios | G68: Suporte Monitor | H68: 9 | I68: 150 | J68: =H68*I68 | K68: =H68*80 | L68: =J68-K68
A69: PED-1068 | B69: 46025 | C69: 2026-01 | D69: Sudeste | E69: Ana Silva | F69: Acessórios | G69: Mouse Vertical | H69: 9 | I69: 220 | J69: =H69*I69 | K69: =H69*120 | L69: =J69-K69
A70: PED-1069 | B70: 46032 | C70: 2026-01 | D70: Nordeste | E70: Beatriz Costa | F70: Acessórios | G70: Mouse Vertical | H70: 7 | I70: 220 | J70: =H70*I70 | K70: =H70*120 | L70: =J70-K70
A71: PED-1070 | B71: 46055 | C71: 2026-02 | D71: Sudeste | E71: Mariana Oliveira | F71: Móveis | G71: Cadeira Ergonômica | H71: 6 | I71: 1200 | J71: =H71*I71 | K71: =H71*750 | L71: =J71-K71
A72: PED-1071 | B72: 46076 | C72: 2026-02 | D72: Sul | E72: Ana Silva | F72: Móveis | G72: Estante de Livros | H72: 7 | I72: 500 | J72: =H72*I72 | K72: =H72*300 | L72: =J72-K72
A73: PED-1072 | B73: 46181 | C73: 2026-06 | D73: Sul | E73: Carlos Souza | F73: Eletrônicos | G73: Smartphone 5G | H73: 7 | I73: 2800 | J73: =H73*I73 | K73: =H73*1900 | L73: =J73-K73
A74: PED-1073 | B74: 46029 | C74: 2026-01 | D74: Sul | E74: Mariana Oliveira | F74: Móveis | G74: Estante de Livros | H74: 4 | I74: 500 | J74: =H74*I74 | K74: =H74*300 | L74: =J74-K74
A75: PED-1074 | B75: 46091 | C75: 2026-03 | D75: Sul | E75: Ana Silva | F75: Móveis | G75: Cadeira Ergonômica | H75: 8 | I75: 1200 | J75: =H75*I75 | K75: =H75*750 | L75: =J75-K75
A76: PED-1075 | B76: 46079 | C76: 2026-02 | D76: Sul | E76: Lucas Ferreira | F76: Móveis | G76: Mesa Escritório L | H76: 4 | I76: 950 | J76: =H76*I76 | K76: =H76*600 | L76: =J76-K76
A77: PED-1076 | B77: 46080 | C77: 2026-02 | D77: Sudeste | E77: Carlos Souza | F77: Móveis | G77: Mesa Escritório L | H77: 5 | I77: 950 | J77: =H77*I77 | K77: =H77*600 | L77: =J77-K77
A78: PED-1077 | B78: 46244 | C78: 2026-08 | D78: Sudeste | E78: Mariana Oliveira | F78: Móveis | G78: Estante de Livros | H78: 9 | I78: 500 | J78: =H78*I78 | K78: =H78*300 | L78: =J78-K78
A79: PED-1078 | B79: 46125 | C79: 2026-04 | D79: Norte | E79: Mariana Oliveira | F79: Eletrônicos | G79: Notebook Gamer | H79: 5 | I79: 4500 | J79: =H79*I79 | K79: =H79*3200 | L79: =J79-K79
A80: PED-1079 | B80: 46068 | C80: 2026-02 | D80: Norte | E80: Mariana Oliveira | F80: Eletrônicos | G80: Notebook Gamer | H80: 10 | I80: 4500 | J80: =H80*I80 | K80: =H80*3200 | L80: =J80-K80
A81: PED-1080 | B81: 46134 | C81: 2026-04 | D81: Nordeste | E81: Mariana Oliveira | F81: Móveis | G81: Estante de Livros | H81: 9 | I81: 500 | J81: =H81*I81 | K81: =H81*300 | L81: =J81-K81
A82: PED-1081 | B82: 46052 | C82: 2026-01 | D82: Centro-Oeste | E82: Beatriz Costa | F82: Eletrônicos | G82: Monitor 27' 144Hz | H82: 1 | I82: 1600 | J82: =H82*I82 | K82: =H82*1100 | L82: =J82-K82
A83: PED-1082 | B83: 46204 | C83: 2026-07 | D83: Centro-Oeste | E83: Ana Silva | F83: Acessórios | G83: Mouse Vertical | H83: 6 | I83: 220 | J83: =H83*I83 | K83: =H83*120 | L83: =J83-K83
A84: PED-1083 | B84: 46133 | C84: 2026-04 | D84: Sudeste | E84: Mariana Oliveira | F84: Acessórios | G84: Webcam Full HD | H84: 2 | I84: 380 | J84: =H84*I84 | K84: =H84*220 | L84: =J84-K84
A85: PED-1084 | B85: 46207 | C85: 2026-07 | D85: Nordeste | E85: Beatriz Costa | F85: Móveis | G85: Estante de Livros | H85: 7 | I85: 500 | J85: =H85*I85 | K85: =H85*300 | L85: =J85-K85
A86: PED-1085 | B86: 46106 | C86: 2026-03 | D86: Centro-Oeste | E86: Mariana Oliveira | F86: Acessórios | G86: Mouse Vertical | H86: 4 | I86: 220 | J86: =H86*I86 | K86: =H86*120 | L86: =J86-K86
A87: PED-1086 | B87: 46130 | C87: 2026-04 | D87: Centro-Oeste | E87: Carlos Souza | F87: Acessórios | G87: Webcam Full HD | H87: 7 | I87: 380 | J87: =H87*I87 | K87: =H87*220 | L87: =J87-K87
A88: PED-1087 | B88: 46163 | C88: 2026-05 | D88: Sudeste | E88: Mariana Oliveira | F88: Móveis | G88: Cadeira Ergonômica | H88: 7 | I88: 1200 | J88: =H88*I88 | K88: =H88*750 | L88: =J88-K88
A89: PED-1088 | B89: 46224 | C89: 2026-07 | D89: Norte | E89: Beatriz Costa | F89: Acessórios | G89: Webcam Full HD | H89: 8 | I89: 380 | J89: =H89*I89 | K89: =H89*220 | L89: =J89-K89
A90: PED-1089 | B90: 46136 | C90: 2026-04 | D90: Centro-Oeste | E90: Carlos Souza | F90: Acessórios | G90: Suporte Monitor | H90: 3 | I90: 150 | J90: =H90*I90 | K90: =H90*80 | L90: =J90-K90
A91: PED-1090 | B91: 46191 | C91: 2026-06 | D91: Sudeste | E91: Mariana Oliveira | F91: Acessórios | G91: Webcam Full HD | H91: 2 | I91: 380 | J91: =H91*I91 | K91: =H91*220 | L91: =J91-K91
A92: PED-1091 | B92: 46232 | C92: 2026-07 | D92: Sul | E92: Mariana Oliveira | F92: Eletrônicos | G92: Smartphone 5G | H92: 3 | I92: 2800 | J92: =H92*I92 | K92: =H92*1900 | L92: =J92-K92
A93: PED-1092 | B93: 46029 | C93: 2026-01 | D93: Sudeste | E93: Carlos Souza | F93: Móveis | G93: Estante de Livros | H93: 2 | I93: 500 | J93: =H93*I93 | K93: =H93*300 | L93: =J93-K93
A94: PED-1093 | B94: 46139 | C94: 2026-04 | D94: Centro-Oeste | E94: Beatriz Costa | F94: Eletrônicos | G94: Headset Sem Fio | H94: 8 | I94: 450 | J94: =H94*I94 | K94: =H94*250 | L94: =J94-K94
A95: PED-1094 | B95: 46125 | C95: 2026-04 | D95: Sul | E95: Carlos Souza | F95: Acessórios | G95: Teclado Mecânico | H95: 2 | I95: 350 | J95: =H95*I95 | K95: =H95*200 | L95: =J95-K95
A96: PED-1095 | B96: 46222 | C96: 2026-07 | D96: Centro-Oeste | E96: Carlos Souza | F96: Eletrônicos | G96: Headset Sem Fio | H96: 1 | I96: 450 | J96: =H96*I96 | K96: =H96*250 | L96: =J96-K96
A97: PED-1096 | B97: 46165 | C97: 2026-05 | D97: Sul | E97: Ana Silva | F97: Móveis | G97: Cadeira Ergonômica | H97: 8 | I97: 1200 | J97: =H97*I97 | K97: =H97*750 | L97: =J97-K97
A98: PED-1097 | B98: 46193 | C98: 2026-06 | D98: Norte | E98: Beatriz Costa | F98: Acessórios | G98: Webcam Full HD | H98: 8 | I98: 380 | J98: =H98*I98 | K98: =H98*220 | L98: =J98-K98
A99: PED-1098 | B99: 46179 | C99: 2026-06 | D99: Norte | E99: Lucas Ferreira | F99: Acessórios | G99: Suporte Monitor | H99: 3 | I99: 150 | J99: =H99*I99 | K99: =H99*80 | L99: =J99-K99
A100: PED-1099 | B100: 46213 | C100: 2026-07 | D100: Centro-Oeste | E100: Lucas Ferreira | F100: Móveis | G100: Cadeira Ergonômica | H100: 5 | I100: 1200 | J100: =H100*I100 | K100: =H100*750 | L100: =J100-K100
...

Sheet Parâmetros
A1: RESUMO POR VENDEDOR | D1: RESUMO POR CATEGORIA | G1: RESUMO POR REGIÃO
A2: Vendedor | B2: Total Faturamento (R$) | D2: Categoria | E2: Total Faturamento (R$) | G2: Região | H2: Total Faturamento (R$)
A3: Ana Silva | B3: =SUMIF('Base de Dados'!E:E, A3, 'Base de Dados'!J:J) | D3: Eletrônicos | E3: =SUMIF('Base de Dados'!F:F, D3, 'Base de Dados'!J:J) | G3: Sudeste | H3: =SUMIF('Base de Dados'!D:D, G3, 'Base de Dados'!J:J)
A4: Carlos Souza | B4: =SUMIF('Base de Dados'!E:E, A4, 'Base de Dados'!J:J) | D4: Móveis | E4: =SUMIF('Base de Dados'!F:F, D4, 'Base de Dados'!J:J) | G4: Sul | H4: =SUMIF('Base de Dados'!D:D, G4, 'Base de Dados'!J:J)
A5: Mariana Oliveira | B5: =SUMIF('Base de Dados'!E:E, A5, 'Base de Dados'!J:J) | D5: Acessórios | E5: =SUMIF('Base de Dados'!F:F, D5, 'Base de Dados'!J:J) | G5: Nordeste | H5: =SUMIF('Base de Dados'!D:D, G5, 'Base de Dados'!J:J)
A6: Lucas Ferreira | B6: =SUMIF('Base de Dados'!E:E, A6, 'Base de Dados'!J:J) | G6: Centro-Oeste | H6: =SUMIF('Base de Dados'!D:D, G6, 'Base de Dados'!J:J)
A7: Beatriz Costa | B7: =SUMIF('Base de Dados'!E:E, A7, 'Base de Dados'!J:J) | G7: Norte | H7: =SUMIF('Base de Dados'!D:D, G7, 'Base de Dados'!J:J)
